MANIFEST.in
README.md
setup.cfg
setup.py
deps/bin/beeline
deps/bin/beeline.cmd
deps/bin/docker-image-tool.sh
deps/bin/find-spark-home
deps/bin/find-spark-home.cmd
deps/bin/load-spark-env.cmd
deps/bin/load-spark-env.sh
deps/bin/pyspark
deps/bin/pyspark.cmd
deps/bin/pyspark2.cmd
deps/bin/run-example
deps/bin/run-example.cmd
deps/bin/spark-class
deps/bin/spark-class.cmd
deps/bin/spark-class2.cmd
deps/bin/spark-connect-shell
deps/bin/spark-shell
deps/bin/spark-shell.cmd
deps/bin/spark-shell2.cmd
deps/bin/spark-sql
deps/bin/spark-sql.cmd
deps/bin/spark-sql2.cmd
deps/bin/spark-submit
deps/bin/spark-submit.cmd
deps/bin/spark-submit2.cmd
deps/bin/sparkR
deps/bin/sparkR.cmd
deps/bin/sparkR2.cmd
deps/data/artifact-tests/crc/junitLargeJar.txt
deps/data/artifact-tests/crc/smallJar.txt
deps/data/graphx/followers.txt
deps/data/graphx/users.txt
deps/data/mllib/gmm_data.txt
deps/data/mllib/kmeans_data.txt
deps/data/mllib/pagerank_data.txt
deps/data/mllib/pic_data.txt
deps/data/mllib/sample_binary_classification_data.txt
deps/data/mllib/sample_fpgrowth.txt
deps/data/mllib/sample_isotonic_regression_libsvm_data.txt
deps/data/mllib/sample_kmeans_data.txt
deps/data/mllib/sample_lda_data.txt
deps/data/mllib/sample_lda_libsvm_data.txt
deps/data/mllib/sample_libsvm_data.txt
deps/data/mllib/sample_linear_regression_data.txt
deps/data/mllib/sample_movielens_data.txt
deps/data/mllib/sample_multiclass_classification_data.txt
deps/data/mllib/sample_svm_data.txt
deps/data/mllib/streaming_kmeans_data_test.txt
deps/data/mllib/als/sample_movielens_ratings.txt
deps/data/mllib/als/test.data
deps/data/mllib/images/license.txt
deps/data/mllib/images/origin/license.txt
deps/data/mllib/images/origin/kittens/not-image.txt
deps/data/mllib/ridge-data/lpsa.data
deps/data/streaming/AFINN-111.txt
deps/examples/__init__.py
deps/examples/als.py
deps/examples/avro_inputformat.py
deps/examples/kmeans.py
deps/examples/logistic_regression.py
deps/examples/pagerank.py
deps/examples/parquet_inputformat.py
pyspark.egg-info/PKG-INFO
pyspark.egg-info/SOURCES.txt
pyspark.egg-info/dependency_links.txt
pyspark.egg-info/requires.txt
pyspark.egg-info/top_level.txt
