Metadata-Version: 2.1
Name: pyspark
Version: 3.5.7
Summary: Apache Spark Python API
Home-page: https://github.com/apache/spark/tree/master/python
Author: Spark Developers
Author-email: dev@spark.apache.org
License: http://www.apache.org/licenses/LICENSE-2.0
Platform: UNKNOWN
Classifier: Development Status :: 5 - Production/Stable
Classifier: License :: OSI Approved :: Apache Software License
Classifier: Programming Language :: Python :: 3.8
Classifier: Programming Language :: Python :: 3.9
Classifier: Programming Language :: Python :: 3.10
Classifier: Programming Language :: Python :: 3.11
Classifier: Programming Language :: Python :: Implementation :: CPython
Classifier: Programming Language :: Python :: Implementation :: PyPy
Classifier: Typing :: Typed
Requires-Python: >=3.8
Provides-Extra: connect
Provides-Extra: ml
Provides-Extra: mllib
Provides-Extra: pandas_on_spark
Provides-Extra: sql
